{"noMoreComments": true, "cursorEnd": 0, "id": "5619799", "comments": [{"postBy": {"location": "\u5f70\u5316\u7e23\u00b7\u53f0\u7063", "utc": 1490530500000, "level": 0, "avatar": "http://filestoresg1.beetalkmobile.com:8081/file/4143727280698998255", "name": "\u507d\u5a18"}, "content": "\u6211\u6c92\u7528\u904e\u773c\u7dda\u7b46\u8036  \u310f\u3002\u3002", "urls": [], "replies": {"first": [], "last": [], "noMoreReplies": true}, "images": [], "id": 61389965}, {"postBy": {"location": "\u53f0\u4e2d\u5e02\u00b7\u53f0\u7063", "utc": 1516196088000, "level": 0, "avatar": "http://filestoresg1.beetalkmobile.com:8081/file/-3141902847222691882", "name": "Sheng"}, "content": "\u597d\u6f02\u4eae\u5594 \u80fd\u4e0d\u80fd\u591a\u8a8d\u8b58\u4f60\u5462 ", "urls": [], "replies": {"first": [], "last": [], "noMoreReplies": true}, "images": [], "id": 79865871}]}
