{"noMoreComments": true, "cursorEnd": 0, "id": "5849008", "comments": [{"postBy": {"location": "\u53f0\u4e2d\u5e02\u00b7\u53f0\u7063", "utc": 1493820118000, "level": 0, "avatar": "http://filestoresg1.beetalkmobile.com:8081/file/-2386995742096877053", "name": "\u77ef\u60c5"}, "content": "\u55ef\u2026<br />\u6211\u627e\u4e00\u500b\u5c08\u9580\u5c04\u7684", "urls": [], "replies": {"first": [], "last": [], "noMoreReplies": true}, "images": [], "id": 64076099}, {"postBy": {"location": "\u53f0\u5357\u5e02\u00b7\u53f0\u7063", "utc": 1493820126000, "level": 0, "avatar": "http://filestoresg1.beetalkmobile.com:8081/file/6610449745407257090", "name": "\u62d2\u7d55"}, "content": "\u5594\ud83d\ude11", "urls": [], "replies": {"first": [], "last": [], "noMoreReplies": true}, "images": [], "id": 64076112}]}
