{"noMoreComments": true, "cursorEnd": 0, "id": "5375675", "comments": [{"postBy": {"location": "\u65b0\u7af9\u5e02\u00b7\u53f0\u7063", "utc": 1486835764000, "level": 0, "avatar": "http://filestoresg1.beetalkmobile.com:8081/file/42842472847939842", "name": "\u963f\u744b"}, "content": "\u52a0\u6211", "urls": [], "replies": {"first": [], "last": [], "noMoreReplies": true}, "images": [], "id": 58492539}, {"postBy": {"location": "\u6843\u5712\u5e02\u00b7\u53f0\u7063", "utc": 1486837493000, "level": 0, "avatar": "http://filestoresg1.beetalkmobile.com:8081/file/-3370651849290286592", "name": "Sacred\u65b0"}, "content": "\u9078\u6211\uff5e!\u9078\u6211\uff5e! \ud83d\ude4b", "urls": [], "replies": {"first": [], "last": [], "noMoreReplies": true}, "images": [], "id": 58493582}, {"postBy": {"location": "\u5f70\u5316\u7e23\u00b7\u53f0\u7063", "utc": 1487947952000, "level": 0, "avatar": "http://filestoresg1.beetalkmobile.com:8081/file/-3252005733318343915", "name": "184"}, "content": "\u55e8\u55e8", "urls": [], "replies": {"first": [], "last": [], "noMoreReplies": true}, "images": [], "id": 59376673}, {"postBy": {"location": "\u53f0\u4e2d\u5e02\u00b7\u53f0\u7063", "utc": 1487956332000, "level": 0, "avatar": "http://filestoresg1.beetalkmobile.com:8081/file/-1573483599367799817", "name": "\u4e0d\u5e25\u4e0d\u5e25\u80fd\u770b\u5c31\u597d"}, "content": "\u52a0\u52a0\u804a\u5929\u8a8d\u8b58\u55ae\u8eab\u597d\u76f8\u8655<br />\u6211\u53ef\u4ee5\u8ddf\u59b3\u7a69\u804a", "urls": [], "replies": {"first": [], "last": [], "noMoreReplies": true}, "images": [], "id": 59385717}]}
