{"noMoreComments": true, "cursorEnd": 0, "id": "5967686", "comments": [{"postBy": {"location": "", "utc": 1495553733000, "level": 0, "avatar": "http://filestoresg1.beetalkmobile.com:8081/file/1333289804742823004", "name": "SickBoy"}, "content": "  ", "urls": [], "replies": {"first": [], "last": [], "noMoreReplies": true}, "images": ["http://filestoresg1.beetalkmobile.com:8081/file/8daf72e081a14f250b828b5e4b67fcb7"], "id": 65405578}, {"postBy": {"location": "\u65b0\u7af9\u7e23\u00b7\u53f0\u7063", "utc": 1495560327000, "level": 0, "avatar": "http://filestoresg1.beetalkmobile.com:8081/file/3986938024755885644", "name": "\u5c0f\u5091"}, "content": "not bad.", "urls": [], "replies": {"first": [], "last": [], "noMoreReplies": true}, "images": [], "id": 65411710}, {"postBy": {"location": "", "utc": 1495560445000, "level": 0, "avatar": "http://filestoresg1.beetalkmobile.com:8081/file/2", "name": "User blocked"}, "content": "\u9084\u597d831\u6536\u6524\u4e86 \u4f60\u53bb\u6536\u7684\u66f4\u5feb", "urls": [], "replies": {"first": [], "last": [], "noMoreReplies": true}, "images": ["http://filestoresg1.beetalkmobile.com:8081/file/2d09b381227d45c9ebeb920be5d0a432"], "id": 65411780}]}
