{"noMoreComments": true, "cursorEnd": 0, "id": "5769074", "comments": [{"postBy": {"location": "\u53f0\u4e2d\u5e02\u00b7\u53f0\u7063", "utc": 1492703450000, "level": 0, "avatar": "http://filestoresg1.beetalkmobile.com:8081/file/-8556105916468177155", "name": "\u55b5\u4ed4\u5377"}, "content": "\u770b\u4e0d\u61c2", "urls": [], "replies": {"first": [], "last": [], "noMoreReplies": true}, "images": [], "id": 63164895}, {"postBy": {"location": "\u65b0\u5317\u5e02\u00b7\u53f0\u7063", "utc": 1531644935000, "level": 0, "avatar": "http://filestoresg1.beetalkmobile.com:8081/file/7480176616824614354", "name": "\u5922\u4e4b\u9047\u8a00"}, "content": "\u53ef\u4ee5\u4ea4\u5f80\u55ce", "urls": [], "replies": {"first": [], "last": [], "noMoreReplies": true}, "images": [], "id": 92392852}, {"postBy": {"location": "\u65b0\u7af9\u5e02\u00b7\u53f0\u7063", "utc": 1531720422000, "level": 0, "avatar": "http://filestoresg1.beetalkmobile.com:8081/file/-6744149233132794364", "name": "\u963f\u6728\u54e5"}, "content": "\u5c31\u662f\u8d70\u4e00\u822c\u7684\u90ca\u5c71\uff0c\u4e0d\u6562\u62c9\u7e69\u6500\u5ca9\u7684\u610f\u601d\u55ce\uff1f", "urls": [], "replies": {"first": [], "last": [], "noMoreReplies": true}, "images": [], "id": 92452541}, {"postBy": {"location": "", "utc": 1532165159000, "level": 0, "avatar": "http://filestoresg1.beetalkmobile.com:8081/file/-4303425838009505788", "name": "\u8521\u5b5f\u7965"}, "content": "\u6211\u5efa\u8b70\u53ef\u4ee5\u53c3\u52a0\u5730\u65b9\u7684\u767b\u5c71\u968a\u958b\u59cb\uff0c\u5f9e\u5c0f\u5c71\u5165\u9580\uff0c\u722c\u51fa\u8208\u8da3\u6216\u9ad4\u80fd\u7df4\u597d\uff0c\u5728\u722c\u767e\u5cb3^_^", "urls": [], "replies": {"first": [], "last": [], "noMoreReplies": true}, "images": [], "id": 92812544}]}
