{"noMoreComments": true, "cursorEnd": 0, "id": "5574049", "comments": [{"postBy": {"location": "", "utc": 1489846875000, "level": 0, "avatar": "http://filestoresg1.beetalkmobile.com:8081/file/-2386995742096877053", "name": "\u77ef\u60c5"}, "content": "\u7b2c13\u95dc", "urls": [], "replies": {"first": [{"content": "\u679c\u7136\u662f\u8ce4\u54e5", "reply": "", "id": 40896531, "name": "\u4f2f\u7235"}], "last": [{"content": "\n\u4f55\u5fc5\u7559\u8a00", "reply": "\u4f2f\u7235", "id": 40896653, "name": "\u77ef\u60c5"}, {"content": "\u54c7\u54a7\u3002\u3002\u3002\u9019\u6a23\u5b50\u4e5f\u53ef\u4ee5\u73a9\u3002\u3002\u3002\u4ec0\u9ebc\u6771\u897f\u554a~\uff01", "reply": "\u77ef\u60c5", "id": 40898289, "name": "\u5f35 \u5c0f\u96e8"}], "noMoreReplies": false}, "images": [], "id": 60831040}, {"postBy": {"location": "\u9ad8\u96c4\u5e02\u00b7\u53f0\u7063", "utc": 1489848652000, "level": 0, "avatar": "http://filestoresg1.beetalkmobile.com:8081/file/6171769892203728055", "name": "\u5584\u7532\u4eba"}, "content": "\u73a9\u523050\u5e7e\u95dc\u8d8a\u73a9\u8d8a\u7121\u804a", "urls": [], "replies": {"first": [], "last": [], "noMoreReplies": true}, "images": [], "id": 60833215}, {"postBy": {"location": "\u57fa\u9686\u5e02\u00b7\u53f0\u7063", "utc": 1489858157000, "level": 0, "avatar": "http://filestoresg1.beetalkmobile.com:8081/file/-9002271241773503992", "name": "Kevin"}, "content": "\u5230\u7b2c\u5341\u4e5f\u6c92\u5f88\u96e3", "urls": [], "replies": {"first": [], "last": [], "noMoreReplies": true}, "images": ["http://filestoresg1.beetalkmobile.com:8081/file/69175eb37aaffb69f0a21c26cecdd953"], "id": 60843467}, {"postBy": {"location": "\u9ad8\u96c4\u5e02\u00b7\u53f0\u7063", "utc": 1489934495000, "level": 0, "avatar": "http://filestoresg1.beetalkmobile.com:8081/file/6933067337067920138", "name": "\u5fae\u98a8"}, "content": "19\u95dc \u5e79", "urls": [], "replies": {"first": [], "last": [], "noMoreReplies": true}, "images": [], "id": 60903290}]}
