{"noMoreComments": true, "cursorEnd": 0, "id": "5888162", "comments": [{"postBy": {"location": "\u53f0\u5317\u5e02\u00b7\u53f0\u7063", "utc": 1494406981000, "level": 0, "avatar": "http://filestoresg1.beetalkmobile.com:8081/file/-7480304138609541120", "name": "SoSo"}, "content": "\u6bcf\u500b\u6708\u90fd\u53ef\u4ee5\u8ddf\u8001\u54e5\u8981\u96d9\u65b0\u978b\u5b50\u771f\u597d", "urls": [], "replies": {"first": [], "last": [], "noMoreReplies": true}, "images": [], "id": 64534339}, {"postBy": {"location": "\u53f0\u5317\u5e02\u00b7\u53f0\u7063", "utc": 1494407115000, "level": 0, "avatar": "http://filestoresg1.beetalkmobile.com:8081/file/-33469117045617809", "name": "\u5c0f\u76ae"}, "content": "\u8001\u54e5os: \u4e0b\u500b\u6708\u8a72\u8b93\u4f60\u7537\u670b\u53cb\u9001\u4e86", "urls": [], "replies": {"first": [], "last": [], "noMoreReplies": true}, "images": [], "id": 64534461}, {"postBy": {"location": "\u5f70\u5316\u7e23\u00b7\u53f0\u7063", "utc": 1494407870000, "level": 0, "avatar": "http://filestoresg1.beetalkmobile.com:8081/file/8930892049168106752", "name": "Big man"}, "content": "\u8cb7\u4e00\u96d9\u978b\u7d66\u6211\uff0c\u5728\u505a\u670b\u53cb", "urls": [], "replies": {"first": [], "last": [], "noMoreReplies": true}, "images": [], "id": 64535132}, {"postBy": {"location": "\u53f0\u4e2d\u5e02\u00b7\u53f0\u7063", "utc": 1494412050000, "level": 0, "avatar": "http://filestoresg1.beetalkmobile.com:8081/file/-6242100111693970456", "name": "\u6392\u7063\u65cf   \u6770~*"}, "content": "\u55ae\u8eab\u6216\u662f\u539f\u4f4f\u6c11\u55ce\uff1f<br />\u63ea\u5718\u641c\u5c0b<br />\uff08\u6b61\u8fce\u539f\u4f4f\u6c11\u4f86\u5230\u90e8\u843d~*\uff09<br />\u6216\u662f<br />\uff08\u55ae\u8eab\u7537\u5973\u4f86\u4f86\u4f86~*\uff09<br /><br />\u6b61\u8fce\u52a0\u5165\u9912\u3002\u3002", "urls": [], "replies": {"first": [], "last": [], "noMoreReplies": true}, "images": [], "id": 64538776}, {"postBy": {"location": "\u5f70\u5316\u7e23\u00b7\u53f0\u7063", "utc": 1494412417000, "level": 0, "avatar": "http://filestoresg1.beetalkmobile.com:8081/file/-6235548138755998413", "name": "\u6b38\u9322"}, "content": "\u6709\u9019\u7a2e\u54e5\u54e5\u771f\u597d", "urls": [], "replies": {"first": [], "last": [], "noMoreReplies": true}, "images": [], "id": 64539090}, {"postBy": {"location": "", "utc": 1494413903000, "level": 0, "avatar": "http://filestoresg1.beetalkmobile.com:8081/file/-1167157964955845375", "name": "\u8cb4\u5148\u751f"}, "content": "\u9019\u978b\u597d\u770b\u5462", "urls": [], "replies": {"first": [], "last": [], "noMoreReplies": true}, "images": [], "id": 64540478}, {"postBy": {"location": "\u9ad8\u96c4\u5e02\u00b7\u53f0\u7063", "utc": 1494418674000, "level": 0, "avatar": "http://filestoresg1.beetalkmobile.com:8081/file/6050570714407455572", "name": "\u9748\u9b42\u6536\u5272\u8005"}, "content": "\u55e8\u4f60\u597d", "urls": [], "replies": {"first": [], "last": [], "noMoreReplies": true}, "images": [], "id": 64545115}, {"postBy": {"location": "\u53f0\u4e2d\u5e02\u00b7\u53f0\u7063", "utc": 1494421290000, "level": 0, "avatar": "http://filestoresg1.beetalkmobile.com:8081/file/3804404804802951474", "name": "\u98db\u7fd4"}, "content": "\u597d\u597d\ud83d\ude02\ud83d\ude02", "urls": [], "replies": {"first": [], "last": [], "noMoreReplies": true}, "images": [], "id": 64547933}, {"postBy": {"location": "\u53f0\u4e2d\u5e02\u00b7\u53f0\u7063", "utc": 1494421576000, "level": 0, "avatar": "http://filestoresg1.beetalkmobile.com:8081/file/3283655193680241987", "name": "\u5091"}, "content": "\u8981\u8cb7\u9019\u96d9\u978b\u8981\u52a0\u6cb9\u54e6,\u76ee\u524d\u770b\u904e\u8ce3\u52303.5W\u7684", "urls": [], "replies": {"first": [], "last": [], "noMoreReplies": true}, "images": [], "id": 64548311}, {"postBy": {"location": "\u65b0\u7af9\u7e23\u00b7\u53f0\u7063", "utc": 1494429082000, "level": 0, "avatar": "http://filestoresg1.beetalkmobile.com:8081/file/-4325672252576466660", "name": "\u4f86\u81eaNG\u4e16\u754c\u7684\u4e00\u676f\u7d05\u8336"}, "content": "\u6700\u8fd1\u4e5f\u53ef\u80fd\u8981\u8cb7\u978b<br />\u81ea\u5f9e\u9019\u4efd\u5de5\u4f5c\u958b\u59cb\uff0c\u6211\u4e00\u5e74\u89812-3\u96d9\u978b<br />\u6bcf\u5929\u5e73\u574710000\u6b65\u4e0a\u4e0b\u2026", "urls": [], "replies": {"first": [], "last": [], "noMoreReplies": true}, "images": [], "id": 64558414}]}
