{"noMoreComments": true, "cursorEnd": 0, "id": "5702733", "comments": [{"postBy": {"location": "", "utc": 1492256568000, "level": 0, "avatar": "http://filestoresg1.beetalkmobile.com:8081/file/-5030263493137435834", "name": "\u7f8a\u4ed4\ud83d\udc0f\ud83d\udc0f\ud83d\udc0f"}, "content": "\u4f60\u9019\u6587\u7ae0\u611f\u89ba\u597d\u50cf\u5948\u5948", "urls": [], "replies": {"first": [{"content": "\u4f60\u53bb\u6b7b\u4ea1\u5427", "reply": "", "id": 42174648, "name": "\u7121\u4eba\u4f7f\u7528"}], "last": [], "noMoreReplies": true}, "images": [], "id": 62788607}]}
