{"noMoreComments": true, "cursorEnd": 0, "id": "5039759", "comments": [{"postBy": {"location": "\u6843\u5712\u5e02\u00b7\u53f0\u7063", "utc": 1481788576000, "level": 0, "avatar": "http://filestoresg1.beetalkmobile.com:8081/file/8052023822854637051", "name": "\u50b2\u5b0c\u5927\u53d4"}, "content": "\u53ea\u807d\u904e\u5403\u80d6\u4e0b\u9762\u6703\u8b8a\u77ed<br /><br />\u6c92\u807d\u904e\u5403\u80d6\u4e0b\u9762\u6703\u8b8a\u7c97<br /><br />\u7d50\u6848\u3002", "urls": [], "replies": {"first": [], "last": [], "noMoreReplies": true}, "images": [], "id": 54602947}, {"postBy": {"location": "\u53f0\u5357\u5e02\u00b7\u53f0\u7063", "utc": 1481791883000, "level": 0, "avatar": "http://filestoresg1.beetalkmobile.com:8081/file/4173973738999134721", "name": "\u754a\u672c\u53cb\u4ed5"}, "content": "\u4f60\u9084\u662f\u56de\u53bb2D\u597d\u4e86", "urls": [], "replies": {"first": [], "last": [], "noMoreReplies": true}, "images": [], "id": 54605921}, {"postBy": {"location": "\u5f70\u5316\u7e23\u00b7\u53f0\u7063", "utc": 1481820958000, "level": 0, "avatar": "http://filestoresg1.beetalkmobile.com:8081/file/-2691260307791060347", "name": "\u6708\u591c\u7434\u4eba"}, "content": "\u4e0d\u77e5\u9053\uff0c<br />\u9019\u662f\u4f60\u770b\u904e\u591a\u5c11\u5927\u53d4\u9ce5\u5f8c\uff0c<br />\u5f97\u51fa\u4f86\u7684\u7d50\u8ad6\u3002", "urls": [], "replies": {"first": [], "last": [], "noMoreReplies": true}, "images": [], "id": 54637253}, {"postBy": {"location": "\u9ad8\u96c4\u5e02\u00b7\u53f0\u7063", "utc": 1481825206000, "level": 0, "avatar": "http://filestoresg1.beetalkmobile.com:8081/file/-2382000672997877927", "name": "\u6f02\u4e3f\u7537\u5b50\u5382"}, "content": "\u6211\u7b11\u4e86....", "urls": [], "replies": {"first": [], "last": [], "noMoreReplies": true}, "images": [], "id": 54640173}]}
