{"noMoreComments": false, "cursorEnd": 23, "id": "5094530", "comments": [{"postBy": {"location": "\u53f0\u4e2d\u5e02\u00b7\u53f0\u7063", "utc": 1482586367000, "level": 0, "avatar": "http://filestoresg1.beetalkmobile.com:8081/file/7697995368686751827", "name": "\u5ca1\u5ca1"}, "content": "\u55e8\u55e8  \u6211\u4e5f\u4e00\u500b\u4eba\u904e\u5462", "urls": [], "replies": {"first": [], "last": [], "noMoreReplies": true}, "images": [], "id": 55220705}, {"postBy": {"location": "\u9ad8\u96c4\u5e02\u00b7\u53f0\u7063", "utc": 1482597854000, "level": 0, "avatar": "http://filestoresg1.beetalkmobile.com:8081/file/-666787824842045952", "name": "\u311a\u5821"}, "content": "\u55e8~ \ud83d\ude0a", "urls": [], "replies": {"first": [], "last": [], "noMoreReplies": true}, "images": [], "id": 55234211}, {"postBy": {"location": "\u53f0\u4e2d\u5e02\u00b7\u53f0\u7063", "utc": 1482607893000, "level": 0, "avatar": "http://filestoresg1.beetalkmobile.com:8081/file/2578197537875046658", "name": "\u871c\u8702\u8981\u639b\u9ede\u4e86"}, "content": "\u4e00\u500b\u4eba\u5728\u5bb6\u7761\u89ba", "urls": [], "replies": {"first": [], "last": [], "noMoreReplies": true}, "images": [], "id": 55240912}, {"postBy": {"location": "\u53f0\u5317\u5e02\u00b7\u53f0\u7063", "utc": 1482621320000, "level": 0, "avatar": "http://filestoresg1.beetalkmobile.com:8081/file/-6123949902876598527", "name": "Joe"}, "content": "\u81ea\u5df1\u73a9\u81ea\u5df1\u7684\u4eba\u4e0d\u5c11", "urls": [], "replies": {"first": [], "last": [], "noMoreReplies": true}, "images": ["http://filestoresg1.beetalkmobile.com:8081/file/011a98864741e50e6066566ff20bb8cf"], "id": 55244580}, {"postBy": {"location": "\u65b0\u5317\u5e02\u00b7\u53f0\u7063", "utc": 1482622094000, "level": 0, "avatar": "http://filestoresg1.beetalkmobile.com:8081/file/-6679822307992264456", "name": "\ud83c\udf39\u6f58\u6735\u62c9\ud83c\udf39"}, "content": "\u8fa3\u59b9\u59b9\u6c34\u5594", "urls": [], "replies": {"first": [], "last": [], "noMoreReplies": true}, "images": [], "id": 55244889}, {"postBy": {"location": "\u65b0\u5317\u5e02\u00b7\u53f0\u7063", "utc": 1482622126000, "level": 0, "avatar": "http://filestoresg1.beetalkmobile.com:8081/file/-1576289539492289328", "name": "CanCer\u6b63"}, "content": "\u65e9\u5b89\uff01\u59b3\u597d", "urls": [], "replies": {"first": [], "last": [], "noMoreReplies": true}, "images": ["http://filestoresg1.beetalkmobile.com:8081/file/448f613652594e9708e476b8689cd88e", "http://filestoresg1.beetalkmobile.com:8081/file/9ab362a520b08dce8764c5a88134fe2f"], "id": 55244909}, {"postBy": {"location": "\u65b0\u5317\u5e02\u00b7\u53f0\u7063", "utc": 1482678832000, "level": 0, "avatar": "http://filestoresg1.beetalkmobile.com:8081/file/2268018395716571927", "name": "\u963f\u4fe1"}, "content": "\u4f86\u53f0\u5317", "urls": [], "replies": {"first": [], "last": [], "noMoreReplies": true}, "images": [], "id": 55293985}, {"postBy": {"location": "\u9ad8\u96c4\u5e02\u00b7\u53f0\u7063", "utc": 1482679136000, "level": 0, "avatar": "http://filestoresg1.beetalkmobile.com:8081/file/2512673259650807574", "name": "\uff2a\uff2a"}, "content": "\u4e5f\u5f88\u597d\ud83d\ude01\ud83d\ude01", "urls": [], "replies": {"first": [], "last": [], "noMoreReplies": true}, "images": [], "id": 55294361}, {"postBy": {"location": "\u5c4f\u6771\u7e23\u00b7\u53f0\u7063", "utc": 1482686820000, "level": 0, "avatar": "http://filestoresg1.beetalkmobile.com:8081/file/-5863045692234991926", "name": "\u53cb\u6607"}, "content": "\u5e73\u51e1\u4e2d\u7684\u5e78\u798f\uff0c\u5feb\u6a02\u8056\u8a95\u7bc0", "urls": [], "replies": {"first": [], "last": [], "noMoreReplies": true}, "images": [], "id": 55302305}, {"postBy": {"location": "\u53f0\u5317\u5e02\u00b7\u53f0\u7063", "utc": 1482693976000, "level": 0, "avatar": "http://filestoresg1.beetalkmobile.com:8081/file/639015283323821609", "name": "~\u5e7e\u5206\u751c\ud83d\udc08\ud83d\udc08\ud83d\udc08~\u6668\u5e0c"}, "content": "\u53ef\u4ee5\u5531\u9673\u5955\u8fc5\u7684\u8056\u8a95\u7bc0 \ud83d\ude38", "urls": [], "replies": {"first": [], "last": [], "noMoreReplies": true}, "images": [], "id": 55306107}, {"postBy": {"location": "\u65b0\u5317\u5e02\u00b7\u53f0\u7063", "utc": 1482712208000, "level": 0, "avatar": "http://filestoresg1.beetalkmobile.com:8081/file/2268018395716571927", "name": "\u963f\u4fe1"}, "content": "\u8056\u8a95\u904e\u4e86\u904e\u8de8\u5e74", "urls": [], "replies": {"first": [], "last": [], "noMoreReplies": true}, "images": [], "id": 55311945}, {"postBy": {"location": "\u6843\u5712\u5e02\u00b7\u53f0\u7063", "utc": 1482721934000, "level": 0, "avatar": "http://filestoresg1.beetalkmobile.com:8081/file/-3848144459751412953", "name": "\ud83c\udde7\ud83c\uddea Brant \ud83d\udeac"}, "content": "\u592a\u8a87\u5f35\u4e86\u22ef", "urls": [], "replies": {"first": [], "last": [], "noMoreReplies": true}, "images": [], "id": 55318347}, {"postBy": {"location": "", "utc": 1482727812000, "level": 0, "avatar": "http://filestoresg1.beetalkmobile.com:8081/file/-2185619096740554482", "name": "Melody"}, "content": "\u662fMerry\uff0c\u4e0d\u662fMarry<br />\ud83d\ude12\ud83d\ude12\ud83d\ude12", "urls": [], "replies": {"first": [], "last": [], "noMoreReplies": true}, "images": ["http://filestoresg1.beetalkmobile.com:8081/file/8ca27b42d5263ada224e6589c0c97003"], "id": 55323099}, {"postBy": {"location": "\u9ad8\u96c4\u5e02\u00b7\u53f0\u7063", "utc": 1482744416000, "level": 0, "avatar": "http://filestoresg1.beetalkmobile.com:8081/file/5096380450882441961", "name": "\u63da"}, "content": "\u5982\u679c\u4e0d\u4ecb\u610f\u6211\u7684\u8a71", "urls": [], "replies": {"first": [], "last": [], "noMoreReplies": true}, "images": [], "id": 55336814}, {"postBy": {"location": "", "utc": 1482745967000, "level": 0, "avatar": "http://filestoresg1.beetalkmobile.com:8081/file/3998044184591744034", "name": "\u865b\u7121\u7e39\u7df2"}, "content": "\u4e5f\u4e0d\u932f\u554a", "urls": [], "replies": {"first": [], "last": [], "noMoreReplies": true}, "images": [], "id": 55338065}, {"postBy": {"location": "\u9ad8\u96c4\u5e02\u00b7\u53f0\u7063", "utc": 1482747803000, "level": 0, "avatar": "http://filestoresg1.beetalkmobile.com:8081/file/-8349833130906125587", "name": "Michael"}, "content": "\u4e0d\u53ef\u80fd\u7684\u4efb\u52d9\u2026", "urls": [], "replies": {"first": [], "last": [], "noMoreReplies": true}, "images": [], "id": 55339717}, {"postBy": {"location": "", "utc": 1482755487000, "level": 0, "avatar": "http://filestoresg1.beetalkmobile.com:8081/file/1071595033363442688", "name": "Stan"}, "content": "\u54ea\u88e1\u9019\u9ebc\u53ef\u611b\u7684\u9e8b\u9e7f\uff0c\u60f3\u5e36\u56de\u5bb6\u4e86\u2764", "urls": [], "replies": {"first": [], "last": [], "noMoreReplies": true}, "images": [], "id": 55347263}, {"postBy": {"location": "\u65b0\u5317\u5e02\u00b7\u53f0\u7063", "utc": 1482757539000, "level": 0, "avatar": "http://filestoresg1.beetalkmobile.com:8081/file/2268018395716571927", "name": "\u963f\u4fe1"}, "content": "go~come", "urls": [], "replies": {"first": [], "last": [], "noMoreReplies": true}, "images": [], "id": 55349521}, {"postBy": {"location": "Taoyuan City\u00b7Taiwan", "utc": 1482761624000, "level": 0, "avatar": "http://filestoresg1.beetalkmobile.com:8081/file/-7890951948460397748", "name": "\u8239\u5e06\u77f3"}, "content": "\u9760\uff0c\u4e0d\u65e9\u8aaa!", "urls": [], "replies": {"first": [], "last": [], "noMoreReplies": true}, "images": [], "id": 55354599}]}
