{"noMoreComments": true, "cursorEnd": 0, "id": "5117802", "comments": [{"postBy": {"location": "\u5609\u7fa9\u5e02\u00b7\u53f0\u7063", "utc": 1483061299000, "level": 0, "avatar": "http://filestoresg1.beetalkmobile.com:8081/file/-6643417476742375483", "name": "\u96a8\u9047\u800c\u5b89"}, "content": "\u71d9\u904e\u8c93\u53ef\u4ee5\u6cbe\u6c99\u62c9\u4e5f\u53ef\u4ee5\u7528\u548c\u98a8\u91ac\u6cb9\uff0c\u6e05\u71c9\u725b\u8089\u9eb5\uff0c", "urls": [], "replies": {"first": [{"content": "\u8c93\u3002\u3002\u3002", "reply": "", "id": 37132111, "name": "\u7d05\u8272\u8033\u6a5f"}, {"content": "(\u904e\u8c93)\u662f\u83dc\u6211\u5fd8\u8a18\u570b\u8a9e\u600e\u8b1b", "reply": "", "id": 37132685, "name": "\u96a8\u9047\u800c\u5b89"}], "last": [], "noMoreReplies": true}, "images": [], "id": 55574693}]}
