{"noMoreComments": true, "cursorEnd": 0, "id": "5707851", "comments": [{"postBy": {"location": "\u9ad8\u96c4\u5e02\u00b7\u53f0\u7063", "utc": 1491781962000, "level": 0, "avatar": "http://filestoresg1.beetalkmobile.com:8081/file/2208638507065025474", "name": "\u89aa\u611b\u7684\u59b3\u8eb2\u5728\u54ea\u88e1\u767c\u5446\ud83c\udf4a "}, "content": "\u4ec0\u9ebc\uff1f \u6709\u770b\u6c92\u6709\u61c2,\u3002\ufe4f\u3002", "urls": [], "replies": {"first": [], "last": [], "noMoreReplies": true}, "images": [], "id": 62424525}]}
