{"noMoreComments": true, "cursorEnd": 0, "id": "5863864", "comments": [{"postBy": {"location": "\u53f0\u4e2d\u5e02\u00b7\u53f0\u7063", "utc": 1494127559000, "level": 0, "avatar": "http://filestoresg1.beetalkmobile.com:8081/file/1225252879198397699", "name": "\u627f\u5b87"}, "content": "\u76f4\u63a5\u52a0\u4f60\u597d\u53cb\u54e6\uff01", "urls": [], "replies": {"first": [], "last": [], "noMoreReplies": true}, "images": [], "id": 64310350}, {"postBy": {"location": "\u53f0\u6771\u7e23\u00b7\u53f0\u7063", "utc": 1494159876000, "level": 0, "avatar": "http://filestoresg1.beetalkmobile.com:8081/file/4307300537608786658", "name": "\u8b1b\u5e79\u8a71\u7684\u5225\u4f86\u7169\u6211"}, "content": "\u8207\u9686\u76f8\u4f34\u7684\u591c\u665a", "urls": [], "replies": {"first": [], "last": [], "noMoreReplies": true}, "images": [], "id": 64340183}, {"postBy": {"location": "\u6843\u5712\u5e02\u00b7\u53f0\u7063", "utc": 1494676186000, "level": 0, "avatar": "http://filestoresg1.beetalkmobile.com:8081/file/9184182165618175571", "name": "\u54a9\u54a9"}, "content": "\u53ef\u4ee5\u52a0\u6211", "urls": [], "replies": {"first": [], "last": [], "noMoreReplies": true}, "images": ["http://filestoresg1.beetalkmobile.com:8081/file/fb3c06914f65fc0f5d126b15a3e497de", "http://filestoresg1.beetalkmobile.com:8081/file/54d70d6b52bc9b32db0da0bb2b326d29"], "id": 64754702}]}
