{"noMoreComments": true, "cursorEnd": 0, "id": "5315130", "comments": [{"postBy": {"location": "\u5f70\u5316\u7e23\u00b7\u53f0\u7063", "utc": 1485954627000, "level": 0, "avatar": "http://filestoresg1.beetalkmobile.com:8081/file/-2514160866675094505", "name": "Sheng Jiun"}, "content": "\u6c92\u5fae\u4fe1\u02ca\u02cb", "urls": [], "replies": {"first": [{"content": "\u54c8\u54c8", "reply": "", "id": 38760553, "name": "Chen\ud83d\udc8b"}, {"content": "\u53ef\u4ee5\u52a0\u5225\u7684\u3107 \u54c8\u54c8", "reply": "Chen\ud83d\udc8b", "id": 38760588, "name": "Sheng Jiun"}], "last": [], "noMoreReplies": true}, "images": [], "id": 57792493}, {"postBy": {"location": "\u5357\u6295\u7e23\u00b7\u53f0\u7063", "utc": 1486055391000, "level": 0, "avatar": "http://filestoresg1.beetalkmobile.com:8081/file/-4083635662730047485", "name": "Ares"}, "content": "\u52a0\u52a0\u52a0\uff5e\uff5e", "urls": [], "replies": {"first": [], "last": [], "noMoreReplies": true}, "images": [], "id": 57880229}]}
