{"noMoreComments": true, "cursorEnd": 0, "id": "5113384", "comments": [{"postBy": {"location": "\u65b0\u7af9\u5e02\u00b7\u53f0\u7063", "utc": 1482914238000, "level": 0, "avatar": "http://filestoresg1.beetalkmobile.com:8081/file/-7499177274545018619", "name": "\u5b5f\u6751"}, "content": "Id 5380225", "urls": [], "replies": {"first": [], "last": [], "noMoreReplies": true}, "images": ["http://filestoresg1.beetalkmobile.com:8081/file/eeb173d1162f72506cb7a0d35d3c50fa"], "id": 55467282}, {"postBy": {"location": "\u5b9c\u862d\u7e23\u00b7\u53f0\u7063", "utc": 1482969683000, "level": 0, "avatar": "http://filestoresg1.beetalkmobile.com:8081/file/-507634615702442652", "name": "\u6797\u8a73\u8aed"}, "content": "Universe", "urls": [], "replies": {"first": [], "last": [], "noMoreReplies": true}, "images": [], "id": 55508697}]}
