{"noMoreComments": true, "cursorEnd": 0, "id": "5655373", "comments": [{"postBy": {"location": "\u65b0\u5317\u5e02\u00b7\u53f0\u7063", "utc": 1491015320000, "level": 0, "avatar": "http://filestoresg1.beetalkmobile.com:8081/file/-9098830344652421886", "name": "\u770b\u770bpo\u6587"}, "content": "\u4f86\u5427 \uff0c\u958b\u5718\u8cfc\u5427", "urls": [], "replies": {"first": [{"content": "\u6211\u53ea\u662f\u5c0f\u5c0f\u54e1\u5de5\u800c\u5df2", "reply": "", "id": 41612173, "name": "\u64fa"}], "last": [], "noMoreReplies": true}, "images": [], "id": 61783130}, {"postBy": {"location": "\u53f0\u4e2d\u5e02\u00b7\u53f0\u7063", "utc": 1491201957000, "level": 0, "avatar": "http://filestoresg1.beetalkmobile.com:8081/file/4383742986332084087", "name": "\u5c0f\u863f"}, "content": "\u597d\u5403\u7684\u6a23\u5b50", "urls": [], "replies": {"first": [{"content": "\u8b1d\u8b1d", "reply": "", "id": 41612157, "name": "\u64fa"}], "last": [], "noMoreReplies": true}, "images": [], "id": 61932231}, {"postBy": {"location": "\u9ad8\u96c4\u5e02\u00b7\u53f0\u7063", "utc": 1491233031000, "level": 0, "avatar": "http://filestoresg1.beetalkmobile.com:8081/file/8104213244059760324", "name": "\ud83d\udc9d \u611b\u7433 \ud83c\udfbc\ud83c\udfb9\ud83c\udfb6\ud83d\udc90"}, "content": "\u770b\u8d77\u4f86\u597d\u5403", "urls": [], "replies": {"first": [{"content": "\u8b1d\u8b1d\u8b9a\u7f8e", "reply": "", "id": 41638721, "name": "\u64fa"}, {"content": "\ud83d\ude00\ud83d\ude00\ud83d\ude00", "reply": "\u64fa", "id": 41638772, "name": "\ud83d\udc9d \u611b\u7433 \ud83c\udfbc\ud83c\udfb9\ud83c\udfb6\ud83d\udc90"}], "last": [], "noMoreReplies": true}, "images": [], "id": 61964836}, {"postBy": {"location": "\u65b0\u5317\u5e02\u00b7\u53f0\u6e7e", "utc": 1491257048000, "level": 0, "avatar": "http://filestoresg1.beetalkmobile.com:8081/file/1989081419530213371", "name": "cello"}, "content": "\u4e0d\u932f\uff0c\u54ea\u8ce3\u5440\uff1f", "urls": [], "replies": {"first": [{"content": "\u864e\u5c3e", "reply": "", "id": 41659063, "name": "\u64fa"}], "last": [], "noMoreReplies": true}, "images": [], "id": 61980192}]}
