{"noMoreComments": true, "cursorEnd": 0, "id": "5015701", "comments": [{"postBy": {"location": "\u5609\u7fa9\u7e23\u00b7\u53f0\u7063", "utc": 1481419590000, "level": 0, "avatar": "http://filestoresg1.beetalkmobile.com:8081/file/-4526783922229507006", "name": "hate"}, "content": "\u55ef\uff0c\u8d0a\u540c", "urls": [], "replies": {"first": [{"content": "\ud83d\ude01\ud83d\ude01\ud83d\ude01", "reply": "", "id": 36191311, "name": "\u5c0f\u744b"}, {"content": "\ud83d\ude04\ud83d\ude01\ud83d\ude1c", "reply": "", "id": 36191692, "name": "hate"}], "last": [], "noMoreReplies": true}, "images": [], "id": 54312042}, {"postBy": {"location": "\u53f0\u5317\u5e02\u00b7\u53f0\u7063", "utc": 1481425833000, "level": 0, "avatar": "http://filestoresg1.beetalkmobile.com:8081/file/-9185673077844678893", "name": "\u812b\u55ae\uff0c\u96e2\u958b\u871c\u8702\u56c9"}, "content": "\u6211\u770b\u4e86\u9019\u908a\uff0c\u9019\u9ebc\u591a\u611f\u60c5\u5931\u6557\u7684\u6587\u7ae0\uff0c\u5916\u8c8c\u548c\u689d\u4ef6\u6bd4\u81ea\u5df1\u66f4\u597d\u7684\u4eba\u90fd\u9047\u4e0d\u5230\u597d\u5c0d\u8c61\uff0c\u8aaa\u5be6\u5728\u70ba\u611f\u60c5\u50b7\u5fc3\u96e3\u904e\u6642\uff0c\u5e38\u5e38\u6703\u60f3\u6b64\u523b\u6211\u5982\u679c\u662f\u55ae\u8eab\u90a3\u8a72\u6709\u591a\u597d\uff0c\u55ae\u8eab\u6642\u53c8\u76fc\u671b\u6709\u500b\u4e86\u89e3\u81ea\u5df1\uff0c\u73cd\u60dc\u75bc\u611b\u81ea\u5df1\u7684\u53e6\u4e00\u4f34\uff0c\u4eba\u7e3d\u662f\u8caa\u5fc3\u7684\u4ec0\u9ebc\u90fd\u60f3\u597d\uff0c\u671f\u671b\u7e3d\u662f\u4e0d\u5982\u9810\u671f\uff0c\u6162\u6162\u5c0b\u627e\uff0c\u614e\u9078\u5c0d\u8c61\uff0c\u883b\u91cd\u8981\u7684\u3002", "urls": [], "replies": {"first": [{"content": "\u611b\u60c5\u8aaa\u4f86\u5c31\u4f86\uff0c\u8aaa\u8d70\u5c31\u8d70\ud83d\ude2d\ud83d\ude2d\ud83d\ude2d", "reply": "", "id": 36208027, "name": "\u5c0f\u744b"}], "last": [], "noMoreReplies": true}, "images": [], "id": 54316950}]}
