{"noMoreComments": true, "cursorEnd": 0, "id": "5671411", "comments": [{"postBy": {"location": "Pingtung County\u00b7Taiwan", "utc": 1491265361000, "level": 0, "avatar": "http://filestoresg1.beetalkmobile.com:8081/file/-1867688723958302501", "name": "Mike"}, "content": "175.........\u6211\u9700\u8981\u62ac\u982d\u8ddf\u4f60\u8b1b\u8a71\u4e86QQ", "urls": [], "replies": {"first": [], "last": [], "noMoreReplies": true}, "images": [], "id": 61983794}, {"postBy": {"location": "\u53f0\u4e2d\u5e02\u00b7\u53f0\u7063", "utc": 1491268011000, "level": 0, "avatar": "http://filestoresg1.beetalkmobile.com:8081/file/4259481674293183444", "name": "\u502b\u502b"}, "content": "\u55e8\u55e8XD ", "urls": [], "replies": {"first": [], "last": [], "noMoreReplies": true}, "images": [], "id": 61985763}, {"postBy": {"location": "\u5357\u6295\u7e23\u00b7\u53f0\u7063", "utc": 1491275574000, "level": 0, "avatar": "http://filestoresg1.beetalkmobile.com:8081/file/-6153976468989086891", "name": "\u963f\u664f"}, "content": "\u592a\u9ad8", "urls": [], "replies": {"first": [], "last": [], "noMoreReplies": true}, "images": [], "id": 61992121}, {"postBy": {"location": "\u5357\u6295\u7e23\u00b7\u53f0\u7063", "utc": 1491275588000, "level": 0, "avatar": "http://filestoresg1.beetalkmobile.com:8081/file/-6153976468989086891", "name": "\u963f\u664f"}, "content": "\u55e8\uff5e\u4e00\u6a23\u9ad8", "urls": [], "replies": {"first": [], "last": [], "noMoreReplies": true}, "images": [], "id": 61992129}]}
